HttpAntiDebug/__init__.py
HttpAntiDebug/__version__.py
HttpAntiDebug/api.py
HttpAntiDebug/exception.py
HttpAntiDebug/response.py
HttpAntiDebug/session.py
HttpAntiDebug-1.0.4.dist-info/LICENSE
HttpAntiDebug-1.0.4.dist-info/METADATA
HttpAntiDebug-1.0.4.dist-info/WHEEL
HttpAntiDebug-1.0.4.dist-info/top_level.txt
HttpAntiDebug-1.0.4.dist-info/RECORD
